alsa_midi/__init__.py
alsa_midi/_ffi.py
alsa_midi/_ffi_defs.py
alsa_midi/address.py
alsa_midi/client.py
alsa_midi/event.py
alsa_midi/exceptions.py
alsa_midi/mido_backend.py
alsa_midi/port.py
alsa_midi/queue.py
alsa_midi/util.py
alsa_midi-1.0.2.dist-info/LICENSE
alsa_midi-1.0.2.dist-info/METADATA
alsa_midi-1.0.2.dist-info/WHEEL
alsa_midi-1.0.2.dist-info/top_level.txt
alsa_midi-1.0.2.dist-info/RECORD
