Metadata-Version: 2.1
Name: alsa-midi
Version: 1.0.2
Summary: Python interface for ALSA MIDI sequencer
License: MIT
Project-URL: GitHub, https://github.com/Jajcus/python-alsa-midi/
Project-URL: Documentation, https://python-alsa-midi.readthedocs.io/
Keywords: ALSA MIDI sequencer
Classifier: License :: OSI Approved :: MIT License
Classifier: Programming Language :: Python :: 3
Classifier: Programming Language :: Python :: 3.7
Classifier: Programming Language :: Python :: 3.8
Classifier: Programming Language :: Python :: 3.9
Classifier: Programming Language :: Python :: 3.10
Classifier: Development Status :: 5 - Production/Stable
Classifier: Framework :: AsyncIO
Classifier: Intended Audience :: Developers
Classifier: Operating System :: POSIX :: Linux
Classifier: Topic :: Multimedia :: Sound/Audio :: MIDI
License-File: LICENSE
Requires-Dist: cffi (>=1.14.0)
Requires-Dist: importlib-metadata ; python_version == "3.7"
